Ranmath/Norms.py
Ranmath/TimeSeriesMatrix.py
Ranmath/__init__.py
Ranmath/CorrelationEstimators/AbstractEstimator.py
Ranmath/CorrelationEstimators/EigenvaluesClippingEstimator.py
Ranmath/CorrelationEstimators/LedoitPecheRIEstimator.py
Ranmath/CorrelationEstimators/LinearShrinkageEstimator.py
Ranmath/CorrelationEstimators/OracleEstimator.py
Ranmath/CorrelationEstimators/PafkaKondorOracleEstimator.py
Ranmath/CorrelationEstimators/QuarticRIEstimator.py
Ranmath/CorrelationEstimators/__init__.py
Ranmath/MatrixDataManagement/MatrixExporter.py
Ranmath/MatrixDataManagement/MatrixImporter.py
Ranmath/MatrixDataManagement/__init__.py
Ranmath/MatrixGenerators/AbstractGenerator.py
Ranmath/MatrixGenerators/ExponentialDecayGenerator.py
Ranmath/MatrixGenerators/InverseWishartGenerator.py
Ranmath/MatrixGenerators/MatrixGeneratorAdapter.py
Ranmath/MatrixGenerators/MultivariateGaussianGenerator.py
Ranmath/MatrixGenerators/__init__.py
Ranmath/MatrixNormalizers/AbstractNormalizer.py
Ranmath/MatrixNormalizers/MatrixNormalizerAdapter.py
Ranmath/MatrixNormalizers/OutlierNormalizer.py
Ranmath/MatrixNormalizers/StandardNormalizer.py
Ranmath/MatrixNormalizers/WinsorizationNormalizer.py
Ranmath/MatrixNormalizers/__init__.py
Ranmath/MatrixReconstructors/AbstractReconstructor.py
Ranmath/MatrixReconstructors/CubeReconstructor.py
Ranmath/MatrixReconstructors/SingleMatrixReconstructor.py
Ranmath/MatrixReconstructors/__init__.py
Ranmath/MatrixSamplers/AbstractSampler.py
Ranmath/MatrixSamplers/GlobalSampler.py
Ranmath/MatrixSamplers/MatrixSamplerAdapter.py
Ranmath/MatrixSamplers/RollingWindowSampler.py
Ranmath/MatrixSamplers/__init__.py
Ranmath/Resolvents/AbstractResolvent.py
Ranmath/Resolvents/C1A1WishartResolvent.py
Ranmath/Resolvents/ExponentialDecayResolvent.py
Ranmath/Resolvents/InvWishExpDecayMixedResolvent.py
Ranmath/Resolvents/InverseWishartResolvent.py
Ranmath/Resolvents/SimulatedEigenvaluesResolvent.py
Ranmath/Resolvents/__init__.py
ranmath-0.1.dist-info/DESCRIPTION.rst
ranmath-0.1.dist-info/METADATA
ranmath-0.1.dist-info/RECORD
ranmath-0.1.dist-info/WHEEL
ranmath-0.1.dist-info/metadata.json
ranmath-0.1.dist-info/top_level.txt
